HdRezkaApi/__init__.py
HdRezkaApi/api.py
HdRezkaApi/errors.py
HdRezkaApi/search.py
HdRezkaApi/session.py
HdRezkaApi/stream.py
HdRezkaApi/types.py
HdRezkaApi-11.1.0.dist-info/METADATA
HdRezkaApi-11.1.0.dist-info/WHEEL
HdRezkaApi-11.1.0.dist-info/top_level.txt
HdRezkaApi-11.1.0.dist-info/RECORD
