Metadata-Version: 2.1
Name: HdRezkaApi
Version: 11.1.0
Summary: HDRezka Python API
Home-page: https://github.com/SuperZombi/HdRezkaApi
Author: Super_Zombi
Author-email: super.zombi.yt@gmail.com
License: UNKNOWN
Project-URL: Documentation, https://superzombi.github.io/HdRezkaApi/
Platform: UNKNOWN
Classifier: Programming Language :: Python :: 3
Classifier: License :: OSI Approved :: MIT License
Classifier: Operating System :: OS Independent
Requires-Python: >=3.9
Requires-Dist: beautifulsoup4
Requires-Dist: requests
